[{"Runs":"9","Balls":"4","Fours":"2","Sixes":"0","StrikeRate":"225.00","Opponent":"DELHI CAPITALS","Venue":"DUBAI","MatchDate":"NOV 10 2020","Result":"MUM INDIANS WON BY 5 WICKETS (WITH 8 BALLS REMAINING)"},{"Runs":"0","Balls":"2","Fours":"0","Sixes":"0","StrikeRate":"0.00","Opponent":"DELHI CAPITALS","Venue":"DUBAI","MatchDate":"NOV 5 2020","Result":"MUM INDIANS WON BY 57 RUNS"},{"Runs":"41","Balls":"25","Fours":"2","Sixes":"4","StrikeRate":"164.00","Opponent":"SUNRISERS HYDERABAD","Venue":"SHARJAH","MatchDate":"NOV 3 2020","Result":"SUNRISERS WON BY 10 WICKETS (WITH 17 BALLS REMAINING)"},{"Runs":"13","Balls":"7","Fours":"1","Sixes":"0","StrikeRate":"185.71","Opponent":"KOLKATA KNIGHT RIDERS","Venue":"ABU DHABI","MatchDate":"SEP 23 2020","Result":"MUM INDIANS WON BY 49 RUNS"},{"Runs":"60","Balls":"24","Fours":"3","Sixes":"5","StrikeRate":"250.00","Opponent":"ROYAL CHALLENGERS BANGALORE","Venue":"DUBAI","MatchDate":"SEP 28 2020","Result":"MATCH TIED (RCB WON THE ONE-OVER ELIMINATOR)"},{"Runs":"18","Balls":"14","Fours":"1","Sixes":"1","StrikeRate":"128.57","Opponent":"CHENNAI SUPER KINGS","Venue":"ABU DHABI","MatchDate":"SEP 19 2020","Result":"SUPER KINGS WON BY 5 WICKETS (WITH 4 BALLS REMAINING)"},{"Runs":"34","Balls":"12","Fours":"1","Sixes":"4","StrikeRate":"283.33","Opponent":"KINGS XI PUNJAB","Venue":"DUBAI","MatchDate":"OCT 18 2020","Result":"MATCH TIED (KINGS XI WON THE ONE-OVER ELIMINATOR)"},{"Runs":"25","Balls":"13","Fours":"0","Sixes":"3","StrikeRate":"192.31","Opponent":"SUNRISERS HYDERABAD","Venue":"SHARJAH","MatchDate":"OCT 4 2020","Result":"MUM INDIANS WON BY 34 RUNS"},{"Runs":"47","Balls":"20","Fours":"3","Sixes":"4","StrikeRate":"235.00","Opponent":"KINGS XI PUNJAB","Venue":"ABU DHABI","MatchDate":"OCT 1 2020","Result":"MUM INDIANS WON BY 48 RUNS"},{"Runs":"11","Balls":"14","Fours":"1","Sixes":"0","StrikeRate":"78.57","Opponent":"DELHI CAPITALS","Venue":"ABU DHABI","MatchDate":"OCT 11 2020","Result":"MUM INDIANS WON BY 5 WICKETS (WITH 2 BALLS REMAINING)"}]